hangul_jamo/__init__.py
hangul_jamo/constants.py
hangul_jamo-1.0.0.dist-info/DESCRIPTION.rst
hangul_jamo-1.0.0.dist-info/METADATA
hangul_jamo-1.0.0.dist-info/RECORD
hangul_jamo-1.0.0.dist-info/WHEEL
hangul_jamo-1.0.0.dist-info/metadata.json
hangul_jamo-1.0.0.dist-info/top_level.txt
