Metadata-Version: 2.0
Name: hangul-jamo
Version: 1.0.0
Summary: A library to compose and decompose Hangul syllables using Hangul jamo characters
Home-page: https://github.com/jonghwanhyeon/hangul-jamo
Author: Jonghwan Hyeon
Author-email: hyeon0145@gmail.com
License: MIT
Keywords: korean hangul syllable jamo composition decomposition
Platform: UNKNOWN
Classifier: Development Status :: 4 - Beta
Classifier: Intended Audience :: Developers
Classifier: Intended Audience :: Science/Research
Classifier: License :: OSI Approved :: MIT License
Classifier: Natural Language :: Korean
Classifier: Programming Language :: Python :: 3
Classifier: Programming Language :: Python :: 3 :: Only
Classifier: Topic :: Scientific/Engineering
Classifier: Topic :: Scientific/Engineering :: Artificial Intelligence
Classifier: Topic :: Scientific/Engineering :: Information Analysis
